{
  "id": "CJ4-01-01",
  "name": "Vyjmenovaná slova po B",
  "order": 1,
  "prerequisite": null,
  "skills": [
    {
      "id": "CJ4-01-01-A",
      "name": "Doplň i/y — vyjmenovaná a odvozená",
      "difficulty": 2,
      "theory": "Vyjmenovaná slova po B: být, bydlit, obyvatel, byt, příbytek, nábytek, dobytek, obyčej, bystrý, bylina, kobyla, býk, Přibyslav.",
      "tasks": [
        {
          "id": "CJ4-01-01-001",
          "type": "choice",
          "question": "Doplň i/y: Ob_vatel domu byl starý pán.",
          "options": [
            "ý — obývatel",
            "i — obivatel",
            "i — obyvatel",
            "í — obívatel",
            "y — obyvatel"
          ],
          "answer": "y — obyvatel",
          "hint": "'Obyvatel' je od 'bydlit' — vyjmenované slovo po B."
        },
        {
          "id": "CJ4-01-01-002",
          "type": "choice",
          "question": "Doplň i/y: Kočka b_la na střeše celou noc.",
          "options": [
            "i — byla",
            "i — bila",
            "ý — býla",
            "y — byla",
            "í — bíla"
          ],
          "answer": "y — byla",
          "hint": "'Byla' je od 'být' — vyjmenované slovo po B."
        },
        {
          "id": "CJ4-01-01-003",
          "type": "choice",
          "question": "Doplň i/y: Novák b_dlí v Praze už deset let.",
          "options": [
            "ý — býdlí",
            "y — bydlí",
            "i — bidlí",
            "í — bídlí",
            "i — bydlí"
          ],
          "answer": "y — bydlí",
          "hint": "'Bydlit' je přímo ve vyjmenovaných slovech po B."
        },
        {
          "id": "CJ4-01-01-004",
          "type": "choice",
          "question": "Doplň i/y: Na farmě chovají dob_tek.",
          "options": [
            "y — dobytek",
            "í — dobítek",
            "ý — dobýtek",
            "i — dobytek",
            "i — dobitek"
          ],
          "answer": "y — dobytek",
          "hint": "'Dobytek' je vyjmenované slovo po B."
        },
        {
          "id": "CJ4-01-01-005",
          "type": "choice",
          "question": "Doplň i/y: V pokoji stojí nový náb_tek.",
          "options": [
            "í — nábítek",
            "ý — nábýtek",
            "y — nábytek",
            "i — nábytek",
            "i — nábitek"
          ],
          "answer": "y — nábytek",
          "hint": "'Nábytek' je vyjmenované slovo po B."
        },
        {
          "id": "CJ4-01-01-006",
          "type": "choice",
          "question": "Doplň i/y: To je starý ob_čej v naší rodině.",
          "options": [
            "i — običej",
            "í — obíčej",
            "i — obyčej",
            "ý — obýčej",
            "y — obyčej"
          ],
          "answer": "y — obyčej",
          "hint": "'Obyčej' je vyjmenované slovo po B."
        },
        {
          "id": "CJ4-01-01-007",
          "type": "choice",
          "question": "Doplň i/y: B_strý chlapec vyřešil úlohu první.",
          "options": [
            "i — bistrý",
            "i — bystrý",
            "y — bystrý",
            "ý — býstrý",
            "í — bístrí"
          ],
          "answer": "y — bystrý",
          "hint": "'Bystrý' je vyjmenované slovo po B."
        },
        {
          "id": "CJ4-01-01-008",
          "type": "choice",
          "question": "Doplň i/y: Babička sbírá léčivé b_liny.",
          "options": [
            "ý — býliny",
            "í — bíliny",
            "i — byliny",
            "i — biliny",
            "y — byliny"
          ],
          "answer": "y — byliny",
          "hint": "'Bylina' je vyjmenované slovo po B."
        },
        {
          "id": "CJ4-01-01-009",
          "type": "choice",
          "question": "Doplň i/y: Kob_la běžela po louce.",
          "options": [
            "y — kobyla",
            "i — kobila",
            "i — kobyla",
            "ý — kobýla",
            "í — kobíla"
          ],
          "answer": "y — kobyla",
          "hint": "'Kobyla' je vyjmenované slovo po B."
        },
        {
          "id": "CJ4-01-01-010",
          "type": "choice",
          "question": "Doplň i/y: B_k stál na pastvině a bučel.",
          "options": [
            "i — býk",
            "í — bík",
            "ý — býk",
            "i — bík",
            "y — býk"
          ],
          "answer": "ý — býk",
          "hint": "'Býk' je vyjmenované slovo po B."
        },
        {
          "id": "CJ4-01-01-011",
          "type": "choice",
          "question": "Doplň i/y: Náš b_t je v třetím patře.",
          "options": [
            "y — byt",
            "i — bit",
            "ý — být",
            "i — byt",
            "í — bít"
          ],
          "answer": "y — byt",
          "hint": "'Byt' je vyjmenované slovo po B."
        },
        {
          "id": "CJ4-01-01-012",
          "type": "choice",
          "question": "Doplň i/y: Dostal starý příb_tek po dědečkovi.",
          "options": [
            "ý — příbýtek",
            "i — příbytek",
            "y — příbytek",
            "í — příbítek",
            "i — příbitek"
          ],
          "answer": "y — příbytek",
          "hint": "'Příbytek' je vyjmenované slovo po B."
        },
        {
          "id": "CJ4-01-01-013",
          "type": "choice",
          "question": "Doplň i/y: Dědeček b_val učitelem.",
          "options": [
            "i — býval",
            "y — býval",
            "í — bíval",
            "i — bíval",
            "ý — býval"
          ],
          "answer": "ý — býval",
          "hint": "'Býval' je od 'být'."
        },
        {
          "id": "CJ4-01-01-014",
          "type": "choice",
          "question": "Doplň i/y: Na adrese je uvedeno b_dliště.",
          "options": [
            "í — bídliště",
            "y — bydliště",
            "i — bidliště",
            "ý — býdliště",
            "i — bydliště"
          ],
          "answer": "y — bydliště",
          "hint": "'Bydliště' je od 'bydlit'."
        },
        {
          "id": "CJ4-01-01-015",
          "type": "choice",
          "question": "Doplň i/y: Ob_dlí starého domu je tmavé.",
          "options": [
            "ý — obýdlí",
            "í — obídlí",
            "i — obydlí",
            "y — obydlí",
            "i — obidlí"
          ],
          "answer": "y — obydlí",
          "hint": "'Obydlí' je od 'bydlit'."
        },
        {
          "id": "CJ4-01-01-016",
          "type": "choice",
          "question": "Doplň i/y: Tady b_vá vždycky veselo.",
          "options": [
            "í — bívá",
            "i — bývá",
            "y — bývá",
            "i — bívá",
            "ý — bývá"
          ],
          "answer": "ý — bývá",
          "hint": "Od 'být'."
        },
        {
          "id": "CJ4-01-01-017",
          "type": "choice",
          "question": "Doplň i/y: Voda v řece přib_vá.",
          "options": [
            "í — přibívá",
            "i — přibývá",
            "i — přibívá",
            "ý — přibývá",
            "y — přibývá"
          ],
          "answer": "ý — přibývá",
          "hint": "'Přibývat' je od 'být'."
        },
        {
          "id": "CJ4-01-01-018",
          "type": "choice",
          "question": "Doplň i/y: Dob_vatelé obsadili hrad.",
          "options": [
            "i — dobivatelé",
            "i — dobyvatelé",
            "y — dobyvatelé",
            "í — dobívatelé",
            "ý — dobývatelé"
          ],
          "answer": "y — dobyvatelé",
          "hint": "'Dobyvatel' je od 'dobýt'."
        },
        {
          "id": "CJ4-01-01-019",
          "type": "choice",
          "question": "Doplň i/y: Zb_tek jídla jsme dali psovi.",
          "options": [
            "ý — zbýtek",
            "i — zbitek",
            "í — zbítek",
            "y — zbytek",
            "i — zbytek"
          ],
          "answer": "y — zbytek",
          "hint": "'Zbytek' je od 'zbýt' — od 'být'."
        },
        {
          "id": "CJ4-01-01-020",
          "type": "choice",
          "question": "Doplň i/y: B_tová jednotka je malý byt.",
          "options": [
            "ý — býtová",
            "i — bitová",
            "i — bytová",
            "í — bítová",
            "y — bytová"
          ],
          "answer": "y — bytová",
          "hint": "Od 'byt'."
        },
        {
          "id": "CJ4-01-01-021",
          "type": "choice",
          "question": "Doplň i/y: Dob_tče uteklo z ohrady.",
          "options": [
            "ý — dobýtče",
            "i — dobitče",
            "í — dobítče",
            "y — dobytče",
            "i — dobytče"
          ],
          "answer": "y — dobytče",
          "hint": "Od 'dobytek'."
        },
        {
          "id": "CJ4-01-01-022",
          "type": "choice",
          "question": "Doplň i/y: Kupovali jsme náb_tkovou stěnu.",
          "options": [
            "y — nábytkovou",
            "i — nábytkovou",
            "í — nábítkovou",
            "i — nábitkovou",
            "ý — nábýtkovou"
          ],
          "answer": "y — nábytkovou",
          "hint": "Od 'nábytek'."
        },
        {
          "id": "CJ4-01-01-023",
          "type": "choice",
          "question": "Doplň i/y: Ob_čejně vstáváme v sedm hodin.",
          "options": [
            "y — obyčejně",
            "ý — obýčejně",
            "í — obíčejně",
            "i — obyčejně",
            "i — običejně"
          ],
          "answer": "y — obyčejně",
          "hint": "Od 'obyčej'."
        },
        {
          "id": "CJ4-01-01-024",
          "type": "choice",
          "question": "Doplň i/y: Potok měl b_strou vodu.",
          "options": [
            "i — bistrou",
            "í — bístrou",
            "y — bystrou",
            "i — bystrou",
            "ý — býstrou"
          ],
          "answer": "y — bystrou",
          "hint": "'Bystrý' = čistý, rychlý."
        },
        {
          "id": "CJ4-01-01-025",
          "type": "choice",
          "question": "Doplň i/y: Pil b_linkový čaj.",
          "options": [
            "i — bylinkový",
            "í — bílinkoví",
            "y — bylinkový",
            "ý — býlinkový",
            "i — bilinkový"
          ],
          "answer": "y — bylinkový",
          "hint": "Od 'bylina'."
        },
        {
          "id": "CJ4-01-01-026",
          "type": "choice",
          "question": "Doplň i/y: B_valý ředitel odešel do důchodu.",
          "options": [
            "ý — bývalý",
            "y — bývalý",
            "í — bívalý",
            "i — bívalí",
            "i — bývalý"
          ],
          "answer": "ý — bývalý",
          "hint": "Od 'být/bývat'."
        },
        {
          "id": "CJ4-01-01-027",
          "type": "choice",
          "question": "Doplň i/y: Zb_tečně jsem se bál.",
          "options": [
            "i — zbitečně",
            "í — zbítečně",
            "y — zbytečně",
            "i — zbytečně",
            "ý — zbýtečně"
          ],
          "answer": "y — zbytečně",
          "hint": "Od 'zbytek/zbýt'."
        },
        {
          "id": "CJ4-01-01-028",
          "type": "choice",
          "question": "Doplň i/y: Neb_lo tam nic zajímavého.",
          "options": [
            "ý — nebýlo",
            "i — nebilo",
            "í — nebílo",
            "y — nebylo",
            "i — nebylo"
          ],
          "answer": "y — nebylo",
          "hint": "Od 'být'."
        },
        {
          "id": "CJ4-01-01-029",
          "type": "choice",
          "question": "Doplň i/y: B_ložravec jí jen rostliny.",
          "options": [
            "i — býložravec",
            "y — býložravec",
            "í — bíložravec",
            "ý — býložravec",
            "i — bíložravec"
          ],
          "answer": "ý — býložravec",
          "hint": "Od 'býlí/bylina'."
        },
        {
          "id": "CJ4-01-01-030",
          "type": "choice",
          "question": "Doplň i/y: Přeb_tek zásob jsme prodali.",
          "options": [
            "í — přebítek",
            "i — přebitek",
            "i — přebytek",
            "ý — přebýtek",
            "y — přebytek"
          ],
          "answer": "y — přebytek",
          "hint": "Od 'přebývat/být'."
        },
        {
          "id": "CJ4-01-01-031",
          "type": "choice",
          "question": "Doplň i/y: Ptáček b_l hnízdo z větviček.",
          "options": [
            "y — bil",
            "í — bíl",
            "y — byl",
            "ý — býl",
            "i — bil"
          ],
          "answer": "i — bil",
          "hint": "'Bít' (udeřit) NENÍ vyjmenované. Ptáček bije zobáčkem."
        },
        {
          "id": "CJ4-01-01-032",
          "type": "choice",
          "question": "Doplň i/y: B_lý sníh pokryl krajinu.",
          "options": [
            "í — bílý",
            "y — bílý",
            "ý — býlý",
            "i — bílý",
            "i — bílí"
          ],
          "answer": "í — bílý",
          "hint": "'Bílý' (barva) NENÍ vyjmenované slovo po B."
        },
        {
          "id": "CJ4-01-01-033",
          "type": "choice",
          "question": "Doplň i/y: Nab_l jsem telefon do plna.",
          "options": [
            "y — nabyl",
            "y — nabil",
            "i — nabil",
            "ý — nabýl",
            "í — nabíl"
          ],
          "answer": "i — nabil",
          "hint": "'Nabít' (telefon) = vložit energii. NENÍ vyjmenované."
        },
        {
          "id": "CJ4-01-01-034",
          "type": "choice",
          "question": "Doplň i/y: Hodiny odb_ly dvanáct.",
          "options": [
            "y — odbyly",
            "y — odbily",
            "ý — odbýly",
            "i — odbily",
            "í — odbíly"
          ],
          "answer": "i — odbily",
          "hint": "Hodiny BIJÍ = vydávají zvuk. Od 'bít'. NENÍ vyjmenované."
        },
        {
          "id": "CJ4-01-01-035",
          "type": "choice",
          "question": "Doplň i/y: B_dlo opřené o zeď spadlo.",
          "options": [
            "í — bídlo",
            "i — bidlo",
            "y — bidlo",
            "y — bydlo",
            "ý — býdlo"
          ],
          "answer": "i — bidlo",
          "hint": "'Bidlo' (tyč) NENÍ vyjmenované slovo po B."
        },
        {
          "id": "CJ4-01-01-036",
          "type": "choice",
          "question": "Doplň i/y: Žili v b_dě a chudobě.",
          "options": [
            "y — bídě",
            "i — bídě",
            "y — býdě",
            "ý — býdě",
            "í — bídě"
          ],
          "answer": "í — bídě",
          "hint": "'Bída' NENÍ vyjmenované slovo po B."
        },
        {
          "id": "CJ4-01-01-037",
          "type": "choice",
          "question": "Doplň i/y: Nab_dka v obchodě byla velká.",
          "options": [
            "í — nabídka",
            "y — nabýdka",
            "i — nabídka",
            "y — nabídka",
            "ý — nabýdka"
          ],
          "answer": "í — nabídka",
          "hint": "'Nabídka' je od 'nabídnout', ne od 'být'."
        },
        {
          "id": "CJ4-01-01-038",
          "type": "choice",
          "question": "Doplň i/y: Sb_rka známek je jeho koníček.",
          "options": [
            "i — sbírka",
            "y — sbýrka",
            "í — sbírka",
            "y — sbírka",
            "ý — sbýrka"
          ],
          "answer": "í — sbírka",
          "hint": "'Sbírka' je od 'sbírat'. NENÍ vyjmenované."
        },
        {
          "id": "CJ4-01-01-039",
          "type": "choice",
          "question": "Doplň i/y: Dob_l jsem kredit na mobilu.",
          "options": [
            "y — dobyl",
            "i — dobil",
            "í — dobíl",
            "ý — dobýl",
            "y — dobil"
          ],
          "answer": "i — dobil",
          "hint": "'Dobít' (kredit) NENÍ vyjmenované. 'Dobýt' (hrad) JE."
        },
        {
          "id": "CJ4-01-01-040",
          "type": "choice",
          "question": "Doplň i/y: B_lek je část vejce.",
          "options": [
            "y — bílek",
            "y — býlek",
            "í — bílek",
            "ý — býlek",
            "i — bílek"
          ],
          "answer": "í — bílek",
          "hint": "'Bílek' je od 'bílý'. NENÍ vyjmenované."
        },
        {
          "id": "CJ4-01-01-041",
          "type": "choice",
          "question": "Doplň i/y: Ob_lí se sklízí v létě.",
          "options": [
            "y — obylí",
            "y — obilí",
            "ý — obýlý",
            "i — obilí",
            "í — obílí"
          ],
          "answer": "i — obilí",
          "hint": "'Obilí' NENÍ vyjmenované slovo po B."
        },
        {
          "id": "CJ4-01-01-042",
          "type": "choice",
          "question": "Doplň i/y: B_dný člověk neměl co jíst.",
          "options": [
            "í — bídný",
            "ý — býdný",
            "y — bídný",
            "i — bídní",
            "i — bídný"
          ],
          "answer": "í — bídný",
          "hint": "'Bídný' od 'bída'. NENÍ vyjmenované."
        },
        {
          "id": "CJ4-01-01-043",
          "type": "choice",
          "question": "Doplň i/y: Sb_ral houby v lese.",
          "options": [
            "ý — sbýral",
            "í — sbíral",
            "y — sbýral",
            "i — sbíral",
            "y — sbíral"
          ],
          "answer": "í — sbíral",
          "hint": "'Sbírat' NENÍ vyjmenované slovo po B."
        },
        {
          "id": "CJ4-01-01-044",
          "type": "choice",
          "question": "Doplň i/y: Maminka b_la prádlo tyčí.",
          "options": [
            "y — byla",
            "y — bila",
            "i — bila",
            "í — bíla",
            "ý — býla"
          ],
          "answer": "i — bila",
          "hint": "'Bít' (mlátit) NENÍ vyjmenované. Bije prádlo = pere."
        },
        {
          "id": "CJ4-01-01-045",
          "type": "choice",
          "question": "Doplň i/y: Zvony b_ly celé odpoledne.",
          "options": [
            "y — byly",
            "i — bily",
            "í — bíly",
            "ý — býly",
            "y — bily"
          ],
          "answer": "i — bily",
          "hint": "Zvony BIJÍ = zvoní úderem. Od 'bít'. NENÍ vyjmenované."
        },
        {
          "id": "CJ4-01-01-046",
          "type": "choice",
          "question": "Doplň i/y: Nab_l jsem nové zkušenosti.",
          "options": [
            "ý — nabýl",
            "i — nabil",
            "i — nabyl",
            "y — nabyl",
            "í — nabíl"
          ],
          "answer": "y — nabyl",
          "hint": "'Nabýt' (získat) je od 'být'. JE vyjmenované."
        },
        {
          "id": "CJ4-01-01-047",
          "type": "choice",
          "question": "Doplň i/y: Dob_li pevnost po třech dnech.",
          "options": [
            "ý — dobýli",
            "i — dobyli",
            "y — dobyli",
            "í — dobíli",
            "i — dobili"
          ],
          "answer": "y — dobyli",
          "hint": "'Dobýt' (zmocnit se) je od 'být'. JE vyjmenované."
        },
        {
          "id": "CJ4-01-01-048",
          "type": "choice",
          "question": "Doplň i/y: Odb_l mě jen krátkou odpovědí.",
          "options": [
            "í — odbíl",
            "ý — odbýl",
            "y — odbyl",
            "i — odbil",
            "i — odbyl"
          ],
          "answer": "y — odbyl",
          "hint": "'Odbýt' (někoho) = zbavit se. Od 'být'. JE vyjmenované."
        },
        {
          "id": "CJ4-01-01-049",
          "type": "choice",
          "question": "Doplň i/y: Ub_valo světla, stmívalo se.",
          "options": [
            "í — ubívalo",
            "i — ubývalo",
            "y — ubývalo",
            "i — ubívalo",
            "ý — ubývalo"
          ],
          "answer": "ý — ubývalo",
          "hint": "'Ubývat' je od 'být'."
        },
        {
          "id": "CJ4-01-01-050",
          "type": "choice",
          "question": "Doplň i/y: Přib_lo nám práce.",
          "options": [
            "i — přibilo",
            "í — přibílo",
            "ý — přibýlo",
            "y — přibylo",
            "i — přibylo"
          ],
          "answer": "y — přibylo",
          "hint": "'Přibýt' je od 'být'."
        }
      ]
    },
    {
      "id": "CJ4-01-01-B",
      "name": "Urči — je to vyjmenované?",
      "difficulty": 2,
      "theory": "Pozor na slova, která NEJSOU vyjmenovaná: bít, bílý, bída, bidlo, bílek, obilí, sbírka.",
      "tasks": [
        {
          "id": "CJ4-01-01-051",
          "type": "choice",
          "question": "Je slovo 'obyvatel' vyjmenované po B nebo odvozené od vyjmenovaného?",
          "options": [
            "Ne, je to cizí slovo",
            "Ne, je odvozené od 'obývat'",
            "Ano, ale jen v množném čísle",
            "Ne, píšeme měkké i",
            "Ano, je odvozené od 'bydlit'"
          ],
          "answer": "Ano, je odvozené od 'bydlit'",
          "hint": "'Obyvatel' je od 'bydlit'."
        },
        {
          "id": "CJ4-01-01-052",
          "type": "choice",
          "question": "Je slovo 'bílý' vyjmenované po B?",
          "options": [
            "Ne, ale píšeme tvrdé y",
            "Ano, je vyjmenované po B",
            "Ano, protože začíná na B",
            "Ano, je odvozené od 'být'",
            "Ne, 'bílý' není vyjmenované — píšeme í"
          ],
          "answer": "Ne, 'bílý' není vyjmenované — píšeme í",
          "hint": "'Bílý' (barva) NENÍ ve vyjmenovaných slovech po B."
        },
        {
          "id": "CJ4-01-01-053",
          "type": "choice",
          "question": "Je slovo 'bída' vyjmenované po B?",
          "options": [
            "Ne, ale píšeme tvrdé y",
            "Ne, 'bída' není vyjmenované — píšeme í",
            "Ano, je odvozené od 'být'",
            "Ano, je vyjmenované po B",
            "Ano, protože začíná na B"
          ],
          "answer": "Ne, 'bída' není vyjmenované — píšeme í",
          "hint": "'Bída' NENÍ ve vyjmenovaných slovech po B."
        },
        {
          "id": "CJ4-01-01-054",
          "type": "choice",
          "question": "Je slovo 'dobytek' vyjmenované po B?",
          "options": [
            "Ano, 'dobytek' je vyjmenované slovo po B",
            "Ne, píšeme měkké i",
            "Ne, je to odvozené od 'dobít'",
            "Ne, je to cizí slovo",
            "Ano, ale jen v 1. pádě"
          ],
          "answer": "Ano, 'dobytek' je vyjmenované slovo po B",
          "hint": "'Dobytek' je přímo ve vyjmenovaných slovech po B."
        },
        {
          "id": "CJ4-01-01-055",
          "type": "choice",
          "question": "Je slovo 'bidlo' vyjmenované po B?",
          "options": [
            "Ano, protože začíná na B",
            "Ano, je vyjmenované po B",
            "Ne, ale píšeme tvrdé y",
            "Ano, je odvozené od 'bydlit'",
            "Ne, 'bidlo' není vyjmenované — píšeme i"
          ],
          "answer": "Ne, 'bidlo' není vyjmenované — píšeme i",
          "hint": "'Bidlo' (tyč) NENÍ ve vyjmenovaných slovech po B."
        },
        {
          "id": "CJ4-01-01-056",
          "type": "choice",
          "question": "Je slovo 'bylina' vyjmenované po B?",
          "options": [
            "Ne, píšeme měkké i",
            "Ne, je to cizí slovo",
            "Ano, 'bylina' je vyjmenované slovo po B",
            "Ano, ale jen v botanice",
            "Ne, je to odvozené od 'bílý'"
          ],
          "answer": "Ano, 'bylina' je vyjmenované slovo po B",
          "hint": "'Bylina' je přímo ve vyjmenovaných slovech po B."
        },
        {
          "id": "CJ4-01-01-057",
          "type": "choice",
          "question": "Je slovo 'sbírka' vyjmenované po B?",
          "options": [
            "Ne, ale píšeme tvrdé y",
            "Ano, je vyjmenované po B",
            "Ano, je odvozené od 'být'",
            "Ne, 'sbírka' není vyjmenované — píšeme í",
            "Ano, protože obsahuje B"
          ],
          "answer": "Ne, 'sbírka' není vyjmenované — píšeme í",
          "hint": "'Sbírka' je od 'sbírat'. NENÍ vyjmenované."
        },
        {
          "id": "CJ4-01-01-058",
          "type": "choice",
          "question": "Je slovo 'kobyla' vyjmenované po B?",
          "options": [
            "Ne, píšeme měkké i",
            "Ano, ale jen v zoologii",
            "Ne, je to cizí slovo",
            "Ano, 'kobyla' je vyjmenované slovo po B",
            "Ne, je to odvozené od 'kobylit'"
          ],
          "answer": "Ano, 'kobyla' je vyjmenované slovo po B",
          "hint": "'Kobyla' je přímo ve vyjmenovaných slovech po B."
        }
      ]
    },
    {
      "id": "CJ4-01-01-C",
      "name": "Vyber správnou větu",
      "difficulty": 2,
      "theory": "Procvičení vyjmenovaných slov po B v celých větách.",
      "tasks": [
        {
          "id": "CJ4-01-01-059",
          "type": "choice",
          "question": "Která věta je napsaná správně?",
          "options": [
            "Obyvatelé města slavili.",
            "Obvyatelé města slavili.",
            "Obivatelé města slavili.",
            "Obivátelé města slavili.",
            "Obývatelé města slavili."
          ],
          "answer": "Obyvatelé města slavili.",
          "hint": "'Obyvatelé' od 'bydlit' — tvrdé y."
        },
        {
          "id": "CJ4-01-01-060",
          "type": "choice",
          "question": "Která věta je napsaná správně?",
          "options": [
            "Bývalí ředitel přišel na návštěvu.",
            "Bívalý ředitel přišel na návštěvu.",
            "Bývalý ředitel přišel na návštěvu.",
            "Bivalý ředitel přišel na návštěvu.",
            "Byvalý ředitel přišel na návštěvu."
          ],
          "answer": "Bývalý ředitel přišel na návštěvu.",
          "hint": "Od 'být/bývat' — tvrdé ý."
        },
        {
          "id": "CJ4-01-01-061",
          "type": "choice",
          "question": "Která věta je napsaná správně?",
          "options": [
            "Bilý kůň stál u plotu.",
            "Býlý kůň stál u plotu.",
            "Bílý kůň stál u plotu.",
            "Bylý kůň stál u plotu.",
            "Bílí kůň stál u plotu."
          ],
          "answer": "Bílý kůň stál u plotu.",
          "hint": "'Bílý' NENÍ vyjmenované — píšeme í."
        },
        {
          "id": "CJ4-01-01-062",
          "type": "choice",
          "question": "Která věta je napsaná správně?",
          "options": [
            "Nabidka v obchodě byla lákavá.",
            "Nabídka v obchodě bila lákavá.",
            "Nabydka v obchodě byla lákavá.",
            "Nabýdka v obchodě byla lákavá.",
            "Nabídka v obchodě byla lákavá."
          ],
          "answer": "Nabídka v obchodě byla lákavá.",
          "hint": "'Nabídka' od 'nabídnout'. NENÍ vyjmenované."
        },
        {
          "id": "CJ4-01-01-063",
          "type": "choice",
          "question": "Která věta je napsaná správně?",
          "options": [
            "Dobýli jsme hrad po dlouhém boji.",
            "Dobyli jsme hrad po dlouhém boji.",
            "Dobilý jsme hrad po dlouhém boji.",
            "Dobíli jsme hrad po dlouhém boji.",
            "Dobili jsme hrad po dlouhém boji."
          ],
          "answer": "Dobyli jsme hrad po dlouhém boji.",
          "hint": "'Dobýt' (zmocnit se) je od 'být'."
        },
        {
          "id": "CJ4-01-01-064",
          "type": "choice",
          "question": "Která věta je napsaná správně?",
          "options": [
            "Nabil pušku a zamíril na terč.",
            "Nabíl pušku a zamířil na terč.",
            "Nabyl pušku a zamířil na terč.",
            "Nabil pušku a zamířil na terč.",
            "Nabýl pušku a zamířil na terč."
          ],
          "answer": "Nabil pušku a zamířil na terč.",
          "hint": "'Nabít' (pušku) = vložit náboj. NENÍ vyjmenované."
        },
        {
          "id": "CJ4-01-01-065",
          "type": "choice",
          "question": "Která věta je napsaná správně?",
          "options": [
            "Zbítek koláče snědl pes.",
            "Zbitek koláče snědl pes.",
            "Zbytek koláče snědl pez.",
            "Zbýtek koláče snědl pes.",
            "Zbytek koláče snědl pes."
          ],
          "answer": "Zbytek koláče snědl pes.",
          "hint": "'Zbytek' od 'zbýt/být'."
        }
      ]
    },
    {
      "id": "CJ4-01-01-D",
      "name": "Třídění — patří / nepatří",
      "difficulty": 2,
      "theory": "Roztřiď slova na vyjmenovaná po B a nevyjmenovaná.",
      "tasks": [
        {
          "id": "CJ4-01-01-066",
          "type": "choice",
          "question": "Které slovo NEPATŘÍ mezi vyjmenovaná po B?",
          "options": [
            "bystrý",
            "bylina",
            "být",
            "bída",
            "bydlit"
          ],
          "answer": "bída",
          "hint": "'Bída' NENÍ ve vyjmenovaných slovech po B."
        },
        {
          "id": "CJ4-01-01-067",
          "type": "choice",
          "question": "Které slovo NEPATŘÍ mezi vyjmenovaná po B?",
          "options": [
            "bič",
            "kobyla",
            "dobytek",
            "obyčej",
            "býk"
          ],
          "answer": "bič",
          "hint": "'Bič' NENÍ ve vyjmenovaných slovech po B."
        },
        {
          "id": "CJ4-01-01-068",
          "type": "choice",
          "question": "Které slovo NEPATŘÍ mezi vyjmenovaná po B?",
          "options": [
            "nábytek",
            "byt",
            "bílý",
            "příbytek",
            "obyvatel"
          ],
          "answer": "bílý",
          "hint": "'Bílý' NENÍ vyjmenované — je to barva."
        },
        {
          "id": "CJ4-01-01-069",
          "type": "choice",
          "question": "Které slovo JE vyjmenované po B?",
          "options": [
            "bidlo",
            "bystrý",
            "bílý",
            "bída",
            "bič"
          ],
          "answer": "bystrý",
          "hint": "'Bystrý' je přímo ve vyjmenovaných slovech po B."
        },
        {
          "id": "CJ4-01-01-070",
          "type": "choice",
          "question": "Které slovo JE odvozené od vyjmenovaného po B?",
          "options": [
            "bičovat",
            "bidýlko",
            "bídný",
            "dobytče",
            "bílek"
          ],
          "answer": "dobytče",
          "hint": "'Dobytče' je od 'dobytek'."
        },
        {
          "id": "CJ4-01-01-071",
          "type": "choice",
          "question": "Které slovo JE odvozené od vyjmenovaného po B?",
          "options": [
            "bílek",
            "bydliště",
            "bičík",
            "bidlo",
            "sbírka"
          ],
          "answer": "bydliště",
          "hint": "'Bydliště' je od 'bydlit'."
        },
        {
          "id": "CJ4-01-01-072",
          "type": "choice",
          "question": "Ve kterém slově píšeme tvrdé Y po B?",
          "options": [
            "obyčej",
            "bidlo",
            "bič",
            "bílek",
            "bída"
          ],
          "answer": "obyčej",
          "hint": "'Obyčej' je vyjmenované slovo po B."
        },
        {
          "id": "CJ4-01-01-073",
          "type": "choice",
          "question": "Ve kterém slově píšeme měkké I po B?",
          "options": [
            "býk",
            "kobyla",
            "bylina",
            "sbírka",
            "bystrý"
          ],
          "answer": "sbírka",
          "hint": "'Sbírka' NENÍ vyjmenované — píšeme měkké í."
        },
        {
          "id": "CJ4-01-01-074",
          "type": "choice",
          "question": "Ve kterém slově píšeme měkké I po B?",
          "options": [
            "obyčej",
            "dobytek",
            "obyvatel",
            "bílý",
            "příbytek"
          ],
          "answer": "bílý",
          "hint": "'Bílý' NENÍ vyjmenované — píšeme měkké í."
        },
        {
          "id": "CJ4-01-01-075",
          "type": "choice",
          "question": "Ve kterém slově píšeme tvrdé Y po B?",
          "options": [
            "bidlo",
            "bída",
            "sbírka",
            "přibývat",
            "nabídka"
          ],
          "answer": "přibývat",
          "hint": "'Přibývat' je od 'být'."
        }
      ]
    },
    {
      "id": "CJ4-01-01-E",
      "name": "Páry — rozliš být/bít, nabýt/nabít...",
      "difficulty": 3,
      "theory": "Pozor na záměny! být × bít, nabýt × nabít, dobýt × dobít, odbýt × odbít.",
      "tasks": [
        {
          "id": "CJ4-01-01-076",
          "type": "choice",
          "question": "'Nabýt' a 'nabít' — jaký je mezi nimi rozdíl?",
          "options": [
            "'Nabýt' = získat (od být), 'nabít' = doplnit energii",
            "'Nabýt' = doplnit energii, 'nabít' = získat",
            "Žádné z nich není vyjmenované",
            "Obě jsou vyjmenovaná",
            "Jsou to stejná slova"
          ],
          "answer": "'Nabýt' = získat (od být), 'nabít' = doplnit energii",
          "hint": "'Nabýt' (získat majetek) je od 'být'. 'Nabít' (baterku) je od 'bít'."
        },
        {
          "id": "CJ4-01-01-077",
          "type": "choice",
          "question": "'Dobýt' a 'dobít' — jaký je mezi nimi rozdíl?",
          "options": [
            "'Dobýt' = doplnit kredit, 'dobít' = zmocnit se",
            "Obě jsou vyjmenovaná",
            "Jsou to stejná slova",
            "Žádné z nich není vyjmenované",
            "'Dobýt' = zmocnit se (od být), 'dobít' = doplnit kredit"
          ],
          "answer": "'Dobýt' = zmocnit se (od být), 'dobít' = doplnit kredit",
          "hint": "'Dobýt' (hrad) je od 'být'. 'Dobít' (kredit) je od 'bít'."
        },
        {
          "id": "CJ4-01-01-078",
          "type": "choice",
          "question": "'Byl' a 'bil' — jaký je mezi nimi rozdíl?",
          "options": [
            "'Byl' = udeřil, 'bil' = existoval",
            "Obě jsou vyjmenovaná",
            "Žádné z nich není vyjmenované",
            "'Byl' = existoval (od být), 'bil' = udeřil (od bít)",
            "Jsou to stejná slova"
          ],
          "answer": "'Byl' = existoval (od být), 'bil' = udeřil (od bít)",
          "hint": "'Být' (existovat) JE vyjmenované. 'Bít' (udeřit) NENÍ."
        },
        {
          "id": "CJ4-01-01-079",
          "type": "choice",
          "question": "'Odbýt' a 'odbít' — jaký je mezi nimi rozdíl?",
          "options": [
            "'Odbýt' = zbavit se někoho (od být), 'odbít' = zaznít úderem",
            "Obě jsou vyjmenovaná",
            "'Odbýt' = zaznít, 'odbít' = zbavit se",
            "Jsou to stejná slova",
            "Žádné z nich není vyjmenované"
          ],
          "answer": "'Odbýt' = zbavit se někoho (od být), 'odbít' = zaznít úderem",
          "hint": "'Odbýt' je od 'být'. 'Odbít' (hodiny odbily) je od 'bít'."
        },
        {
          "id": "CJ4-01-01-080",
          "type": "choice",
          "question": "'Bydlo' a 'bidlo' — jaký je mezi nimi rozdíl?",
          "options": [
            "Obě jsou vyjmenovaná",
            "'Bydlo' = obydlí (od bydlit, vyjm.), 'bidlo' = tyč (není vyjm.)",
            "Žádné z nich není vyjmenované",
            "Jsou to stejná slova",
            "'Bydlo' = tyč, 'bidlo' = obydlí"
          ],
          "answer": "'Bydlo' = obydlí (od bydlit, vyjm.), 'bidlo' = tyč (není vyjm.)",
          "hint": "'Bydlo' je od 'bydlit'. 'Bidlo' (tyč) NENÍ vyjmenované."
        }
      ]
    },
    {
      "id": "CJ4-01-01-F",
      "name": "Doplň i/y — mix a opakování",
      "difficulty": 2,
      "theory": "Souhrn všech vyjmenovaných slov po B.",
      "tasks": [
        {
          "id": "CJ4-01-01-081",
          "type": "choice",
          "question": "Doplň i/y: B_čí zápas jsme viděli v televizi.",
          "options": [
            "i — býčí",
            "ý — býčí",
            "i — bíčí",
            "y — býčí",
            "í — bíčí"
          ],
          "answer": "ý — býčí",
          "hint": "Od 'býk'."
        },
        {
          "id": "CJ4-01-01-082",
          "type": "choice",
          "question": "Doplň i/y: Na kob_lce hraje dítě.",
          "options": [
            "ý — kobýlce",
            "i — kobylce",
            "í — kobílce",
            "y — kobylce",
            "i — kobilce"
          ],
          "answer": "y — kobylce",
          "hint": "Od 'kobyla'. Kobylka = hmyz."
        },
        {
          "id": "CJ4-01-01-083",
          "type": "choice",
          "question": "Doplň i/y: B_dlení v centru je drahé.",
          "options": [
            "i — bidlení",
            "í — bídlení",
            "y — bydlení",
            "i — bydlení",
            "ý — býdlení"
          ],
          "answer": "y — bydlení",
          "hint": "Od 'bydlit'."
        },
        {
          "id": "CJ4-01-01-084",
          "type": "choice",
          "question": "Doplň i/y: Přeb_tek peněz nemáme.",
          "options": [
            "y — přebytek",
            "i — přebitek",
            "í — přebítek",
            "ý — přebýtek",
            "i — přebytek"
          ],
          "answer": "y — přebytek",
          "hint": "Od 'přebývat/být'."
        },
        {
          "id": "CJ4-01-01-085",
          "type": "choice",
          "question": "Doplň i/y: Sm_čcový orchestr hrál krásně.",
          "options": [
            "ý — smýčcový",
            "i — smičcový",
            "y — smyčcový",
            "í — smíčcoví",
            "i — smyčcový"
          ],
          "answer": "y — smyčcový",
          "hint": "Pozor — tohle je po M, ne po B! Smyčec od smýkat."
        },
        {
          "id": "CJ4-01-01-086",
          "type": "choice",
          "question": "Doplň i/y: B_tovka je druh domu.",
          "options": [
            "ý — býtovka",
            "í — bítovka",
            "y — bytovka",
            "i — bytovka",
            "i — bitovka"
          ],
          "answer": "y — bytovka",
          "hint": "Od 'byt'."
        },
        {
          "id": "CJ4-01-01-087",
          "type": "choice",
          "question": "Doplň i/y: Neb_t tebe, nepřišel bych.",
          "options": [
            "i — nebýt",
            "ý — nebýt",
            "í — nebít",
            "i — nebít",
            "y — nebýt"
          ],
          "answer": "ý — nebýt",
          "hint": "'Nebýt' od 'být'."
        },
        {
          "id": "CJ4-01-01-088",
          "type": "choice",
          "question": "Doplň i/y: Zab_dlel se v novém městě.",
          "options": [
            "i — zabidlel",
            "í — zabídlel",
            "i — zabydlel",
            "ý — zabýdlel",
            "y — zabydlel"
          ],
          "answer": "y — zabydlel",
          "hint": "Od 'bydlit'."
        },
        {
          "id": "CJ4-01-01-089",
          "type": "choice",
          "question": "Doplň i/y: B_tost je živá věc.",
          "options": [
            "i — bitost",
            "y — bytost",
            "i — bytost",
            "í — bítost",
            "ý — býtost"
          ],
          "answer": "y — bytost",
          "hint": "Od 'být'. Bytost = jsoucno."
        },
        {
          "id": "CJ4-01-01-090",
          "type": "choice",
          "question": "Doplň i/y: Om_l slova, která nechtěl říct.",
          "options": [
            "i — omyl",
            "ý — omýl",
            "í — omíl",
            "i — omil",
            "y — omyl"
          ],
          "answer": "y — omyl",
          "hint": "Pozor — tohle je po M! 'Omyl' od 'mýlit se'."
        },
        {
          "id": "CJ4-01-01-091",
          "type": "choice",
          "question": "Doplň i/y: B_valé koupaliště chátrá.",
          "options": [
            "y — bývalé",
            "i — bývalé",
            "í — bívalé",
            "ý — bývalé",
            "i — bívalé"
          ],
          "answer": "ý — bývalé",
          "hint": "Od 'být/bývat'."
        },
        {
          "id": "CJ4-01-01-092",
          "type": "choice",
          "question": "Doplň i/y: Neob_čejný příběh nás zaujal.",
          "options": [
            "i — neobyčejný",
            "i — neobičejný",
            "ý — neobýčejný",
            "í — neobíčejní",
            "y — neobyčejný"
          ],
          "answer": "y — neobyčejný",
          "hint": "Od 'obyčej'."
        },
        {
          "id": "CJ4-01-01-093",
          "type": "choice",
          "question": "Doplň i/y: M_val je noční zvíře.",
          "options": [
            "ý — mýval",
            "í — míval",
            "y — mýval",
            "i — míval",
            "i — mýval"
          ],
          "answer": "ý — mýval",
          "hint": "Pozor — tohle je po M! 'Mýval' od 'mýt'."
        },
        {
          "id": "CJ4-01-01-094",
          "type": "choice",
          "question": "Doplň i/y: Ob_čejný den se změnil v dobrodružství.",
          "options": [
            "i — obyčejný",
            "y — obyčejný",
            "ý — obýčejný",
            "i — običejný",
            "í — obíčejní"
          ],
          "answer": "y — obyčejný",
          "hint": "Od 'obyčej'."
        },
        {
          "id": "CJ4-01-01-095",
          "type": "choice",
          "question": "Doplň i/y: B_strá řeka tekla údolím.",
          "options": [
            "y — bystrá",
            "i — bystrá",
            "í — bístrá",
            "i — bistrá",
            "ý — býstrá"
          ],
          "answer": "y — bystrá",
          "hint": "Od 'bystrý'."
        },
        {
          "id": "CJ4-01-01-096",
          "type": "choice",
          "question": "Doplň i/y: Odp_kal si trest ve vězení.",
          "options": [
            "í — odpíkal",
            "y — odpykal",
            "i — odpykal",
            "i — odpikal",
            "ý — odpýkal"
          ],
          "answer": "y — odpykal",
          "hint": "Pozor — tohle je po P! 'Pykat' je vyjmenované po P."
        },
        {
          "id": "CJ4-01-01-097",
          "type": "choice",
          "question": "Doplň i/y: Přib_slavský zámek je krásný.",
          "options": [
            "í — přibíslavskí",
            "i — přibyslavský",
            "i — přibislavský",
            "y — přibyslavský",
            "ý — přibýslavský"
          ],
          "answer": "y — přibyslavský",
          "hint": "Od 'Přibyslav'."
        },
        {
          "id": "CJ4-01-01-098",
          "type": "choice",
          "question": "Doplň i/y: B_linkový sirup chutná dobře.",
          "options": [
            "i — bilinkový",
            "í — bílinkoví",
            "i — bylinkový",
            "y — bylinkový",
            "ý — býlinkový"
          ],
          "answer": "y — bylinkový",
          "hint": "Od 'bylina'."
        },
        {
          "id": "CJ4-01-01-099",
          "type": "choice",
          "question": "Doplň i/y: Odb_t zákazníka není slušné.",
          "options": [
            "i — odbýt",
            "i — odbít",
            "ý — odbýt",
            "í — odbít",
            "y — odbýt"
          ],
          "answer": "ý — odbýt",
          "hint": "'Odbýt' = zbavit se někoho. Od 'být'."
        },
        {
          "id": "CJ4-01-01-100",
          "type": "choice",
          "question": "Doplň i/y: B_t či neb_t, to je otázka.",
          "options": [
            "i — být, nebýt",
            "ý — být, nebýt",
            "i — bít, nebít",
            "y — být, nebýt",
            "í — bít, nebýt"
          ],
          "answer": "ý — být, nebýt",
          "hint": "'Být' je vyjmenované slovo po B."
        }
      ]
    }
  ]
}